{
  "@context": {
    "@language": "en",
    "@vocab": "https://schema.org/",
    "cr": "http://mlcommons.org/croissant/",
    "geocr": "http://mlcommons.org/geocroissant/",
    "dct": "http://purl.org/dc/terms/",
    "sc": "https://schema.org/",
    "citeAs": "cr:citeAs",
    "column": "cr:column",
    "conformsTo": "dct:conformsTo",
    "data": {
      "@id": "cr:data",
      "@type": "@json"
    },
    "dataBiases": "cr:dataBiases",
    "dataCollection": "cr:dataCollection",
    "dataType": {
      "@id": "cr:dataType",
      "@type": "@vocab"
    },
    "extract": "cr:extract",
    "field": "cr:field",
    "fileProperty": "cr:fileProperty",
    "fileObject": "cr:fileObject",
    "format": "cr:format",
    "includes": "cr:includes",
    "isLiveDataset": "cr:isLiveDataset",
    "jsonPath": "cr:jsonPath",
    "key": "cr:key",
    "md5": {
      "@id": "cr:md5",
      "@type": "sc:Text"
    },
    "sha256": {
      "@id": "cr:sha256",
      "@type": "sc:Text"
    },
    "parentField": "cr:parentField",
    "path": "cr:path",
    "personalSensitiveInformation": "cr:personalSensitiveInformation",
    "recordSet": "cr:recordSet",
    "references": "cr:references",
    "regex": "cr:regex",
    "repeated": "cr:repeated",
    "replace": "cr:replace",
    "separator": "cr:separator",
    "source": "cr:source",
    "subField": "cr:subField",
    "transform": "cr:transform"
  },
  "@type": "Dataset",
  "@id": "CMIP6.ScenarioMIP.KIOST.KIOST-ESM.ssp585.r1i1p1f1.Amon.tas.gr1.v20191106",
  "name": "CMIP6.ScenarioMIP.KIOST.KIOST-ESM.ssp585.r1i1p1f1.Amon.tas.gr1.v20191106",
  "description": "CMIP6 climate model output dataset.",
  "version": "v1",
  "license": "CC-BY-4.0",
  "conformsTo": "http://mlcommons.org/croissant/1.0",
  "creator": {
    "@type": "Organization",
    "name": "Unknown"
  },
  "publisher": {
    "@type": "Organization",
    "name": "Centre for Environmental Data Analysis (CEDA)"
  },
  "citation": "CMIP6 climate model output. ScenarioMIP experiment by KIOST-ESM under ssp585 scenario.",
  "isAccessibleForFree": true,
  "includedInDataCatalog": {
    "@type": "DataCatalog",
    "name": "CEDA Archive",
    "url": "https://catalogue.ceda.ac.uk/"
  },
  "spatialCoverage": {
    "@type": "Place",
    "geo": {
      "@type": "GeoShape",
      "box": "-90.0 -179.0625 90.0 179.0625"
    }
  },
  "temporalCoverage": "2015-01-17T12:00:00Z/2100-12-17T12:00:00Z",
  "url": "https://api.stac.ceda.ac.uk/collections/cmip6/items/CMIP6.ScenarioMIP.KIOST.KIOST-ESM.ssp585.r1i1p1f1.Amon.tas.gr1.v20191106",
  "keywords": [
    "CMIP6",
    "climate",
    "ssp585",
    "tas",
    "ScenarioMIP",
    "temperature",
    "KIOST"
  ],
  "variableMeasured": [
    {
      "@type": "PropertyValue",
      "name": "tas",
      "description": "Near surface air temperature"
    }
  ],
  "dataCollection": {
    "@type": "DataCollection",
    "name": "Coupled Model Intercomparison Project Phase 6 (CMIP6)"
  },
  "datePublished": "2015-01-17T12:00:00Z",
  "dct:temporal": {
    "startDate": "2015-01-17T12:00:00Z",
    "endDate": "2100-12-17T12:00:00Z"
  },
  "geocr:BoundingBox": [
    -179.0625,
    -90.0,
    179.0625,
    90.0
  ],
  "geocr:summaries": {
    "platform": [],
    "instruments": []
  },
  "references": [
    {
      "@type": "CreativeWork",
      "url": "https://api.stac.ceda.ac.uk/collections/cmip6/items/CMIP6.ScenarioMIP.KIOST.KIOST-ESM.ssp585.r1i1p1f1.Amon.tas.gr1.v20191106",
      "name": "STAC Item",
      "encodingFormat": "application/json"
    }
  ],
  "distribution": [
    {
      "@type": "cr:FileObject",
      "name": "reference_file",
      "description": "reference_file",
      "contentUrl": "https://dap.ceda.ac.uk/badc/cmip6/metadata/kerchunk/pipeline1/ScenarioMIP/KIOST/KIOST-ESM/kr1.0/CMIP6_ScenarioMIP_KIOST_KIOST-ESM_ssp585_r1i1p1f1_Amon_tas_gr1_v20191106_kr1.0.json",
      "encodingFormat": "application/zstd"
    },
    {
      "@type": "cr:FileObject",
      "name": "data0001",
      "description": "data0001",
      "contentUrl": "https://dap.ceda.ac.uk/badc/cmip6/data/CMIP6/ScenarioMIP/KIOST/KIOST-ESM/ssp585/r1i1p1f1/Amon/tas/gr1/v20191106/tas_Amon_KIOST-ESM_ssp585_r1i1p1f1_gr1_201501-210012.nc",
      "encodingFormat": "application/netcdf"
    }
  ],
  "recordSet": [
    {
      "@type": "cr:RecordSet",
      "name": "CMIP6-records",
      "field": [
        {
          "@type": "cr:Field",
          "name": "time",
          "description": "Time of measurement"
        },
        {
          "@type": "cr:Field",
          "name": "tas",
          "description": "Near surface air temperature (K)"
        }
      ]
    }
  ]
}